<?xml version="1.0" encoding="UTF-8"?>
<StringCodeDatabase Version="2" ItemsCount="45"><StringCode SourceType="DLLRC:"><StringId>@{concretecheck.2een.2ecdd.2edeflection.2e1d2d.2ew7_4.2edescription}</StringId>
		<SourceDll>CodeDependentDeflections.2edll</SourceDll>
		<ResourceId>1065</ResourceId>
	</StringCode>
	<StringCode SourceType="DLLRC:"><StringId>@{codedependentdeflections.2erc_ids_cdd_deflection_check_delta_imm_z}</StringId>
		<SourceDll>CodeDependentDeflections.2edll</SourceDll>
		<ResourceId>1044</ResourceId>
	</StringCode>
	<StringCode SourceType="DLLRC:"><StringId>@{codedependentdeflections.2erc_ids_cdd_deflection_check_delta_imm_y}</StringId>
		<SourceDll>CodeDependentDeflections.2edll</SourceDll>
		<ResourceId>1043</ResourceId>
	</StringCode>
	<StringCode SourceType="DLLRC:"><StringId>@{codedependentdeflections.2erc_ids_cdd_deflection_check_delta_imm}</StringId>
		<SourceDll>CodeDependentDeflections.2edll</SourceDll>
		<ResourceId>1042</ResourceId>
	</StringCode>
	<StringCode SourceType="DLLRC:"><StringId>@{codedependentdeflections.2erc_ids_cdd_deflection_check_brief_table_name_2d}</StringId>
		<SourceDll>CodeDependentDeflections.2edll</SourceDll>
		<ResourceId>1003</ResourceId>
	</StringCode>
	<StringCode SourceType="DLLRC:"><StringId>@{codedependentdeflections.2erc_ids_cdd_deflection_check_delta_creepshort_y}</StringId>
		<SourceDll>CodeDependentDeflections.2edll</SourceDll>
		<ResourceId>1056</ResourceId>
	</StringCode>
	<StringCode SourceType="DLLRC:"><StringId>@{codedependentdeflections.2erc_ids_cdd_deflection_check_delta_creeplong}</StringId>
		<SourceDll>CodeDependentDeflections.2edll</SourceDll>
		<ResourceId>1058</ResourceId>
	</StringCode>
	<StringCode SourceType="DLLRC:"><StringId>@{codedependentdeflections.2erc_ids_cdd_deflection_check_delta_creepshort_z}</StringId>
		<SourceDll>CodeDependentDeflections.2edll</SourceDll>
		<ResourceId>1057</ResourceId>
	</StringCode>
	<StringCode SourceType="DLLRC:"><StringId>@{codedependentdeflections.2erc_ids_cdd_deflection_check_delta_creepshort}</StringId>
		<SourceDll>CodeDependentDeflections.2edll</SourceDll>
		<ResourceId>1055</ResourceId>
	</StringCode>
	<StringCode SourceType="DLLRC:"><StringId>@{concretecheck.2een.2ecdd.2edeflection.2e1d2d.2ew7_7.2edescription}</StringId>
		<SourceDll>CodeDependentDeflections.2edll</SourceDll>
		<ResourceId>1069</ResourceId>
	</StringCode>
	<StringCode SourceType="DLLRC:"><StringId>@{codedependentdeflections.2erc_ids_cdd_deflection_check_uc}</StringId>
		<SourceDll>CodeDependentDeflections.2edll</SourceDll>
		<ResourceId>1004</ResourceId>
	</StringCode>
	<StringCode SourceType="DLLRC:"><StringId>@{concretecheck.2een.2ecdd.2edeflection.2e1d.2ew7_2.2edescription}</StringId>
		<SourceDll>CodeDependentDeflections.2edll</SourceDll>
		<ResourceId>1063</ResourceId>
	</StringCode>
	<StringCode SourceType="DLLRC:"><StringId>@{concretecheck.2een.2ecdd.2edeflection.2e1d.2ew7_1.2edescription}</StringId>
		<SourceDll>CodeDependentDeflections.2edll</SourceDll>
		<ResourceId>1062</ResourceId>
	</StringCode>
	<StringCode SourceType="DLLRC:"><StringId>@{concretecheck.2een.2ecdd.2edeflection.2e1d2d.2en7_1.2edescription}</StringId>
		<SourceDll>CodeDependentDeflections.2edll</SourceDll>
		<ResourceId>1072</ResourceId>
	</StringCode>
	<StringCode SourceType="DLLRC:"><StringId>@{codedependentdeflections.2erc_ids_cdd_deflection_check_delta_add_lim}</StringId>
		<SourceDll>CodeDependentDeflections.2edll</SourceDll>
		<ResourceId>1014</ResourceId>
	</StringCode>
	<StringCode SourceType="DLLRC:"><StringId>@{codedependentdeflections.2erc_ids_cdd_deflection_check_delta_add_z}</StringId>
		<SourceDll>CodeDependentDeflections.2edll</SourceDll>
		<ResourceId>1013</ResourceId>
	</StringCode>
	<StringCode SourceType="DLLRC:"><StringId>@{codedependentdeflections.2erc_ids_cdd_deflection_check_delta_add_y}</StringId>
		<SourceDll>CodeDependentDeflections.2edll</SourceDll>
		<ResourceId>1012</ResourceId>
	</StringCode>
	<StringCode SourceType="DLLRC:"><StringId>@{codedependentdeflections.2erc_ids_cdd_deflection_check_delta_add}</StringId>
		<SourceDll>CodeDependentDeflections.2edll</SourceDll>
		<ResourceId>1011</ResourceId>
	</StringCode>
	<StringCode SourceType="DLLRC:"><StringId>@{concretecheck.2een.2ecdd.2edeflection.2e1d2d.2ew7_6.2edescription}</StringId>
		<SourceDll>CodeDependentDeflections.2edll</SourceDll>
		<ResourceId>1068</ResourceId>
	</StringCode>
	<StringCode SourceType="DLLRC:"><StringId>@{concretecheck.2een.2ecdd.2edeflection.2e1d2d.2ewarning.2ecss.2edimensions.2esolution}</StringId>
		<SourceDll>CodeDependentDeflections.2edll</SourceDll>
		<ResourceId>1070</ResourceId>
	</StringCode>
	<StringCode SourceType="DLLRC:"><StringId>@{codedependentdeflections.2erc_ids_cdd_deflection_check_delta_tot_lim}</StringId>
		<SourceDll>CodeDependentDeflections.2edll</SourceDll>
		<ResourceId>1008</ResourceId>
	</StringCode>
	<StringCode SourceType="DLLRC:"><StringId>@{codedependentdeflections.2erc_ids_cdd_deflection_check_delta_tot_z}</StringId>
		<SourceDll>CodeDependentDeflections.2edll</SourceDll>
		<ResourceId>1007</ResourceId>
	</StringCode>
	<StringCode SourceType="DLLRC:"><StringId>@{codedependentdeflections.2erc_ids_cdd_deflection_check_delta_tot_y}</StringId>
		<SourceDll>CodeDependentDeflections.2edll</SourceDll>
		<ResourceId>1006</ResourceId>
	</StringCode>
	<StringCode SourceType="DLLRC:"><StringId>@{codedependentdeflections.2erc_ids_cdd_deflection_check_delta_tot}</StringId>
		<SourceDll>CodeDependentDeflections.2edll</SourceDll>
		<ResourceId>1005</ResourceId>
	</StringCode>
	<StringCode SourceType="DLLRC:"><StringId>@{codedependentdeflections.2erc_ids_cdd_deflection_check_delta_creep_z}</StringId>
		<SourceDll>CodeDependentDeflections.2edll</SourceDll>
		<ResourceId>1050</ResourceId>
	</StringCode>
	<StringCode SourceType="DLLRC:"><StringId>@{codedependentdeflections.2erc_ids_cdd_deflection_check_delta_creep_y}</StringId>
		<SourceDll>CodeDependentDeflections.2edll</SourceDll>
		<ResourceId>1049</ResourceId>
	</StringCode>
	<StringCode SourceType="DLLRC:"><StringId>@{codedependentdeflections.2erc_ids_cdd_deflection_check_delta_creep}</StringId>
		<SourceDll>CodeDependentDeflections.2edll</SourceDll>
		<ResourceId>1048</ResourceId>
	</StringCode>
	<StringCode SourceType="DLLRC:"><StringId>@{concretecheck.2een.2ecdd.2edeflection.2e1d2d.2ew7_5.2edescription}</StringId>
		<SourceDll>CodeDependentDeflections.2edll</SourceDll>
		<ResourceId>1066</ResourceId>
	</StringCode>
	<StringCode SourceType="DLLRC:"><StringId>@{concretecheck.2een.2ecdd.2edeflection.2e1d.2ee09.2edescription}</StringId>
		<SourceDll>CodeDependentDeflections.2edll</SourceDll>
		<ResourceId>1071</ResourceId>
	</StringCode>
	<StringCode SourceType="DLLRC:"><StringId>@{concretecheck.2een.2ecdd.2edeflection.2e1d2d.2ew7_8.2edescription}</StringId>
		<SourceDll>CodeDependentDeflections.2edll</SourceDll>
		<ResourceId>1125</ResourceId>
	</StringCode>
	<StringCode SourceType="DLLRC:"><StringId>@{concretecheck.2een.2ecdd.2edeflection.2e1d2d.2ew7_5.2esolution}</StringId>
		<SourceDll>CodeDependentDeflections.2edll</SourceDll>
		<ResourceId>1067</ResourceId>
	</StringCode>
	<StringCode SourceType="DLLRC:"><StringId>@{codedependentdeflections.2erc_ids_cdd_deflection_check_delta_add_lim_z}</StringId>
		<SourceDll>CodeDependentDeflections.2edll</SourceDll>
		<ResourceId>1016</ResourceId>
	</StringCode>
	<StringCode SourceType="DLLRC:"><StringId>@{codedependentdeflections.2erc_ids_cdd_deflection_check_delta_add_lim_y}</StringId>
		<SourceDll>CodeDependentDeflections.2edll</SourceDll>
		<ResourceId>1015</ResourceId>
	</StringCode>
	<StringCode SourceType="DLLRC:"><StringId>@{codedependentdeflections.2erc_ids_cdd_deflection_check_delta_lin_z}</StringId>
		<SourceDll>CodeDependentDeflections.2edll</SourceDll>
		<ResourceId>1019</ResourceId>
	</StringCode>
	<StringCode SourceType="DLLRC:"><StringId>@{codedependentdeflections.2erc_ids_cdd_deflection_check_delta_tot_lim_z}</StringId>
		<SourceDll>CodeDependentDeflections.2edll</SourceDll>
		<ResourceId>1010</ResourceId>
	</StringCode>
	<StringCode SourceType="DLLRC:"><StringId>@{codedependentdeflections.2erc_ids_cdd_deflection_check_delta_lin_y}</StringId>
		<SourceDll>CodeDependentDeflections.2edll</SourceDll>
		<ResourceId>1018</ResourceId>
	</StringCode>
	<StringCode SourceType="DLLRC:"><StringId>@{codedependentdeflections.2erc_ids_cdd_deflection_check_delta_tot_lim_y}</StringId>
		<SourceDll>CodeDependentDeflections.2edll</SourceDll>
		<ResourceId>1009</ResourceId>
	</StringCode>
	<StringCode SourceType="DLLRC:"><StringId>@{codedependentdeflections.2erc_ids_cdd_deflection_check_delta_lin}</StringId>
		<SourceDll>CodeDependentDeflections.2edll</SourceDll>
		<ResourceId>1017</ResourceId>
	</StringCode>
	<StringCode SourceType="DLLRC:"><StringId>@{concretecheck.2een.2ecdd.2edeflection.2e1d2d.2ew7_3.2edescription}</StringId>
		<SourceDll>CodeDependentDeflections.2edll</SourceDll>
		<ResourceId>1064</ResourceId>
	</StringCode>
	<StringCode SourceType="DLLRC:"><StringId>@{codedependentdeflections.2erc_ids_cdd_deflection_check_delta_short_z}</StringId>
		<SourceDll>CodeDependentDeflections.2edll</SourceDll>
		<ResourceId>1047</ResourceId>
	</StringCode>
	<StringCode SourceType="DLLRC:"><StringId>@{codedependentdeflections.2erc_ids_cdd_deflection_check_delta_creeplong_y}</StringId>
		<SourceDll>CodeDependentDeflections.2edll</SourceDll>
		<ResourceId>1059</ResourceId>
	</StringCode>
	<StringCode SourceType="DLLRC:"><StringId>@{codedependentdeflections.2erc_ids_cdd_deflection_check_delta_short_y}</StringId>
		<SourceDll>CodeDependentDeflections.2edll</SourceDll>
		<ResourceId>1046</ResourceId>
	</StringCode>
	<StringCode SourceType="DLLRC:"><StringId>@{codedependentdeflections.2erc_ids_cdd_deflection_check_delta_short}</StringId>
		<SourceDll>CodeDependentDeflections.2edll</SourceDll>
		<ResourceId>1045</ResourceId>
	</StringCode>
	<StringCode SourceType="DLLRC:"><StringId>@{codedependentdeflections.2erc_ids_cdd_deflection_check_delta_creeplong_z}</StringId>
		<SourceDll>CodeDependentDeflections.2edll</SourceDll>
		<ResourceId>1061</ResourceId>
	</StringCode>
	<StringCode SourceType="DLLRC:"><StringId>@{codedependentdeflections.2erc_ids_cdd_deflection_check_brief_table_name_1d}</StringId>
		<SourceDll>CodeDependentDeflections.2edll</SourceDll>
		<ResourceId>1002</ResourceId>
	</StringCode>
</StringCodeDatabase>
